{
  "_class": "artboard",
  "backgroundColor": {
    "_class": "color",
    "alpha": 1,
    "blue": 0.9686274509803922,
    "green": 0.9686274509803922,
    "red": 0.9686274509803922
  },
  "booleanOperation": -1,
  "clippingMaskMode": 0,
  "do_objectID": "ABA40C39-E48C-42E8-806B-D036162FD4E3",
  "exportOptions": {
    "_class": "exportOptions",
    "exportFormats": [
      {
        "_class": "exportFormat",
        "absoluteSize": 0,
        "fileFormat": "png",
        "name": "",
        "namingScheme": 0,
        "scale": 1,
        "visibleScaleType": 0
      }
    ],
    "includedLayerIds": [
    ],
    "layerOptions": 2,
    "shouldTrim": false
  },
  "frame": {
    "_class": "rect",
    "constrainProportions": false,
    "height": 1034,
    "width": 1366,
    "x": -658,
    "y": 5024
  },
  "groupLayout": {
    "_class": "MSImmutableFreeformGroupLayout"
  },
  "hasBackgroundColor": true,
  "hasClickThrough": true,
  "hasClippingMask": false,
  "horizontalRulerData": {
    "_class": "rulerData",
    "base": 0,
    "guides": [
    ]
  },
  "includeBackgroundColorInExport": true,
  "includeInCloudUpload": true,
  "isFixedToViewport": false,
  "isFlippedHorizontal": false,
  "isFlippedVertical": false,
  "isFlowHome": false,
  "isLocked": false,
  "isVisible": true,
  "layerListExpandedType": 2,
  "layers": [
    {
      "class": "group",
      "id": "FB543F85-6397-40AA-9221-BD9EBDB3D5B6"
    },
    {
      "class": "symbolInstance",
      "id": "FA90E9FF-625E-4570-9D9D-4DF3E632148B"
    },
    {
      "class": "group",
      "id": "C4634CD6-3B0C-4369-BA1A-1BA81E2CDD77"
    },
    {
      "class": "symbolInstance",
      "id": "37BE6F81-8A78-4CEA-81F3-49AB4F0C3B5C"
    },
    {
      "class": "symbolInstance",
      "id": "C12F7B3D-936D-49B5-98B3-3AAE79ACF75E"
    },
    {
      "class": "symbolInstance",
      "id": "84E95BDE-0B74-4C66-AB2C-83C04B6FE9AE"
    }
  ],
  "name": "Loan / Truy vấn & Trả nợ - 5",
  "nameIsFixed": true,
  "presetDictionary": {
  },
  "resizesContent": false,
  "resizingConstraint": 63,
  "resizingType": 0,
  "rotation": 0,
  "shouldBreakMaskChain": true,
  "style": {
    "_class": "style",
    "blur": {
      "_class": "blur",
      "center": "{0.5, 0.5}",
      "isEnabled": false,
      "motionAngle": 0,
      "radius": 10,
      "saturation": 1,
      "type": 0
    },
    "borderOptions": {
      "_class": "borderOptions",
      "dashPattern": [
      ],
      "isEnabled": true,
      "lineCapStyle": 0,
      "lineJoinStyle": 0
    },
    "borders": [
    ],
    "colorControls": {
      "_class": "colorControls",
      "brightness": 0,
      "contrast": 1,
      "hue": 0,
      "isEnabled": false,
      "saturation": 1
    },
    "contextSettings": {
      "_class": "graphicsContextSettings",
      "blendMode": 0,
      "opacity": 1
    },
    "do_objectID": "A29BFE97-3011-4AA3-9E18-94AB1736857B",
    "endMarkerType": 0,
    "fills": [
    ],
    "innerShadows": [
    ],
    "miterLimit": 10,
    "shadows": [
    ],
    "startMarkerType": 0,
    "windingRule": 1
  },
  "userInfo": {
    "com.abynim.sketchplugins.userflows": {
      "artboardID": "ABA40C39-E48C-42E8-806B-D036162FD4E3"
    }
  },
  "verticalRulerData": {
    "_class": "rulerData",
    "base": 0,
    "guides": [
    ]
  }
}